indigochem/__init__.py
indigochem/bingo.py
indigochem/indigo.py
indigochem/indigo_inchi.py
indigochem/indigo_renderer.py
indigochemo-0.1.data/scripts/indigo.py
indigochemo-0.1.dist-info/METADATA
indigochemo-0.1.dist-info/WHEEL
indigochemo-0.1.dist-info/top_level.txt
indigochemo-0.1.dist-info/RECORD
