Metadata-Version: 2.1
Name: indigochemo
Version: 0.1
Summary: Indigo chemoinformatics packaged for pip. Software and all rights owned by EPAM (https://lifescience.opensource.epam.com).
Home-page: UNKNOWN
Author: Deepak Kumar
Author-email: 
License: UNKNOWN
Platform: UNKNOWN
Classifier: Programming Language :: Python :: 3
Classifier: License :: OSI Approved :: MIT License
Classifier: Operating System :: OS Independent
